<?xml version="1.0"?>
<game_state>
	<window />
	<input />
	<textures />
	<audio />
	<battleScene />
	<scene />
	<mainmenu />
	<mainmenu />
	<entitymanager>
		<Player>
			<player1>
				<Position x="3.32197857" y="16.4499302" Map_ID="1" Player_Map_ID="2" />
				<Stats Life="30" Attack="10" />
			</player1>
		</Player>
		<NPCs>
			<NPC1>
				<Position x="13.8999996" y="1.89999998" />
				<State Has_Combat="false" Has_Talked="false" />
			</NPC1>
		</NPCs>
		<Enemies />
		<Allies />
	</entitymanager>
	<guiManager />
	<dialoguemanager />
	<renderer />
</game_state>
